CHANGELOG.md
LICENSE
README.md
pyproject.toml
setup.py
benchmark/README.md
benchmark/test_pykonal_figure_3.py
benchmark/test_pykonal_figure_4.py
benchmark/test_pykonal_figure_5.py
benchmark/test_pykonal_figure_6.py
benchmark/test_pykonal_figure_7.py
benchmark/test_pykonal_figure_8.py
benchmark/pykonal/figure_3.py
benchmark/pykonal/figure_4.py
benchmark/pykonal/figure_5.py
benchmark/pykonal/figure_6.py
benchmark/pykonal/figure_7.py
benchmark/pykonal/figure_8.py
data/mitp2008.npz
data/marmousi2/marmousi2.npz
data/marmousiVTI/marmeta.bin
data/marmousiVTI/marmvx.bin
data/marmousiVTI/marmvz.bin
demos/test_pyekfmm_fig1.py
demos/test_pyekfmm_fig2-multishots.py
demos/test_pyekfmm_fig2.py
demos/test_pyekfmm_fig3.py
demos/test_pyekfmm_fig4.py
demos/test_pyekfmm_fig4_xnoty.py
demos/test_pyekfmm_fig5.py
demos/test_pyekfmm_raytracing2d_benchmarkWITHbhtomo.py
demos/test_pyekfmm_raytracing3d.py
demos/test_pyekfmm_raytracing3d_reciprocal.py
demos/test_pyekfmm_takeoff_dip_and_azim.py
pyekfmm/__init__.py
pyekfmm/coordinates.py
pyekfmm/fmm.py
pyekfmm/fmmvti.py
pyekfmm/plot.py
pyekfmm/stream.py
pyekfmm/tomo.py
pyekfmm/vel.py
pyekfmm.egg-info/PKG-INFO
pyekfmm.egg-info/SOURCES.txt
pyekfmm.egg-info/dependency_links.txt
pyekfmm.egg-info/not-zip-safe
pyekfmm.egg-info/requires.txt
pyekfmm.egg-info/top_level.txt
pyekfmm/src/eikonal.c
pyekfmm/src/eikonalvti.c